lkml/__init__.py
lkml/__main__.py
lkml/keys.py
lkml/lexer.py
lkml/parser.py
lkml/py.typed
lkml/simple.py
lkml/tokens.py
lkml/tree.py
lkml/utils.py
lkml/visitors.py
lkml-1.3.7.dist-info/LICENSE.md
lkml-1.3.7.dist-info/METADATA
lkml-1.3.7.dist-info/WHEEL
lkml-1.3.7.dist-info/entry_points.txt
lkml-1.3.7.dist-info/top_level.txt
lkml-1.3.7.dist-info/RECORD
