Metadata-Version: 2.2
Name: lkml
Version: 1.3.7
Summary: A speedy LookML parser implemented in pure Python.
Home-page: https://github.com/joshtemple/lkml
Download-URL: https://github.com/joshtemple/lkml/tarball/1.3.7
Author: Josh Temple
Author-email: 
License: MIT
Keywords: lookml looker parser
Classifier: Development Status :: 5 - Production/Stable
Classifier: Intended Audience :: Developers
Classifier: License :: OSI Approved :: MIT License
Classifier: Programming Language :: Python :: 3.7
Classifier: Topic :: Software Development
License-File: LICENSE.md
Dynamic: author
Dynamic: classifier
Dynamic: description
Dynamic: description-content-type
Dynamic: download-url
Dynamic: home-page
Dynamic: keywords
Dynamic: license
Dynamic: summary
